advancedrequests/__init__.py
advancedrequests-1.0.4.dist-info/METADATA
advancedrequests-1.0.4.dist-info/WHEEL
advancedrequests-1.0.4.dist-info/top_level.txt
advancedrequests-1.0.4.dist-info/RECORD
