Metadata-Version: 2.1
Name: advancedrequests
Version: 1.0.4
Summary: Makes advanced requests
Home-page: UNKNOWN
Author: GigaAlex
Author-email: nick.faltermeier@gmx.de
License: UNKNOWN
Keywords: python
Platform: UNKNOWN
Classifier: Operating System :: Microsoft :: Windows
